Workbook
Name \s: #REF!
Name \w: #REF!
Name _ALC30: '[1]STAFF WITH OT'!#REF!
Name _AMC30: '[1]STAFF WITH OT'!#REF!
Name _Top50: #REF!
Name a: #REF!
Name aa: #REF!
Name AcF_Val: #REF!
Name AcI_Val: #REF!
Name AcM_Val: #REF!
Name activity: [2]Grade!$G$12:$G$56
Name afadsfsadfadsfadsfads: #REF!
Name ALL_GRADES: '[3]group job master list'!#REF!
Name Allowances: #REF!
Name BaseLessRegionalAllowance1: #REF!
Name BaseSalary1: #REF!
Name bonus_0: [4]EmployeeMaster!$AV$6:$AV$23
Name bonus_1: [4]Micro!$D$19
Name bonus_1_r: [4]EmployeeMaster!$AM$6:$AM$23
Name bonus_p_07: [5]EmployeeMaster!#REF!
Name bonusid: [4]EmployeeMaster!$D$6:$D$23
Name By_grade: #REF!
Name by_grd: #REF!
Name by_grde: #REF!
Name by_Survey_Benchmark_Role: #REF!
Name by_Survey_Family_Code: #REF!
Name by_Survey_Position_Code: #REF!
Name ByNationality: #REF!
Name ByOwnership: #REF!
Name ByRegion: #REF!
Name CarBenefit1: #REF!
Name co: [5]EmployeeMaster!$E$6:$E$1784
Name Construction: '[6]STAFF WITH OT'!#REF!
Name CountryComp: #REF!
Name current_year: #REF!
Name d: #REF!
Name eligible_years_of_service: [7]Data!$T$27086
Name external_factors: [5]Macro!$C$5:$I$29
Name f: #REF!
Name FamilyAll: #REF!
Name FamilyNats: #REF!
Name FamilyNonNats: #REF!
Name ff: #REF!
Name Format2Print: #REF!
Name g: #REF!
Name General_Market: #REF!
Name GeneralMarket: #REF!
Name gg: #REF!
Name HayPoints1: #REF!
Name KHB_Val: #REF!
Name KHHRS_Val: #REF!
Name kkk: #REF!
Name LetterVal: #REF!
Name LIST_AGE_GRP: '[3]group job master list'!#REF!
Name LIST_BU: '[3]group job master list'!#REF!
Name LIST_CO: '[3]group job master list'!#REF!
Name LIST_GRD: '[3]group job master list'!#REF!
Name LIST_NAT: '[3]group job master list'!#REF!
Name LIST_NAT_GRP: '[3]group job master list'!#REF!
Name LIST_POSITIONS: '[3]group job master list'!#REF!

Sheet employee_master1
F2: =TODAY() -> 46130 | N2: Current | O2: EMP DETAILS | T2: emp.status | V2: Allowns | AG2: Total Cash (Bonus) | AI2: other staff cost
A3: Emp_id | B3: Emp-Name | C3: job_name | D3: reports_to_name | E3: reports_to_id | F3: doj | G3: contract end date | H3: Service Years | I3: DOB | J3: Age | K3: Family St. | L3: CCHI Card Type | M3: Total Salary | N3: Basic Salary | O3: Nat ID | P3: Nat | Q3: REGON | R3: passport id | S3: iqama id or national id | T3: emp. Status (active/withdrawn) | U3: contract type | V3: OT Allow | W3: loa | X3: House Allown | Y3: Rent | Z3: transportation allown | AA3: car_cost_monthly | AB3: alow_spe | AC3: alow_proj | AD3: alow_food | AE3: alow_others | AF3: ALT Annual Leave Ticket | AG3: Bonus Eligibility Months | AH3: Bonus (tot amount divided by 12 for pm cost) SR | AI3: GOSI p.m SR | AJ3: Indemnity pm SR | AK3: Leave Accrual SR | AL3: med_insr SR | AM3: pa_insr & life SR
A4: MJ-001 | B4: KHALID FOUAD | C4: VIC BOARD | F4: 46113 | G4: =F4+365 -> 46478 | H4: =DATEDIF(F4, TODAY(), "Y") -> 0 | I4: 29809 | J4: =DATEDIF(I4, TODAY(), "Y") -> 44 | K4: F | L4: B | M4: =N4+X4+Z4+AA4+AB4+AC4+AD4+AE4+AG4 -> 16000 | N4: 11851.852 | O4: SD | P4: Sudanes | Q4: Riyadh | S4: 2499342026 | T4: active | U4: full time | V4: =N4/30/80*1.25 -> 6.1728395 | W4: 0 | X4: =N4*0.25 -> 2962.963 | Y4: 0 | Z4: =N4*0.1 -> 1185.1852 | AA4: 0 | AB4: 0 | AC4: 0 | AD4: 0 | AE4: 0 | AF4: 0 | AG4: 0 | AH4: =N4*AG4 -> 0 | AI4: =(N4+X4)*0.02 -> 296.2963 | AJ4: =N4/30*H4 -> 0 | AK4: =N4/30*2.5 -> 987.65432 | AL4: 0 | AM4: 53
A5: MJ-002 | B5: SABRI OMER | C5: Director Mangar | D5: KAHID FOUAD | E5: GM | F5: 45597 | G5: =F5+365 -> 45962 | H5: =DATEDIF(F5, TODAY(), "Y") -> 1 | I5: 33604 | J5: =DATEDIF(I5, TODAY(), "Y") -> 34 | K5: F | L5: B | M5: =N5+X5+Z5+AA5+AB5+AC5+AD5+AE5+AG5 -> 13999.5 | N5: 10370 | O5: SD | P5: Sudanes | Q5: Riyadh | T5: active | U5: full time | V5: =N5/30/80*1.25 -> 5.4010417 | W5: 0 | X5: =N5*0.25 -> 2592.5 | Y5: 0 | Z5: =N5*0.1 -> 1037 | AA5: 0 | AB5: 0 | AC5: 0 | AD5: 0 | AE5: 0 | AF5: 0 | AG5: 0 | AH5: =N5*AG5 -> 0 | AI5: =(N5+X5)*0.02 -> 259.25 | AJ5: =N5/30*H5 -> 345.66667 | AK5: =N5/30*2.5 -> 864.16667 | AL5: 0 | AM5: 53
A6: MJ-003 | B6: MOHAMMED ALARABI | C6: MANAGEMENT | D6: KAHID FOUAD | E6: GM | F6: 45597 | G6: =F6+365 -> 45962 | H6: =DATEDIF(F6, TODAY(), "Y") -> 1 | I6: 29587 | J6: =DATEDIF(I6, TODAY(), "Y") -> 45 | K6: F | L6: B | M6: =N6+X6+Z6+AA6+AB6+AC6+AD6+AE6+AG6 -> 13999.5 | N6: 10370 | O6: SD | P6: Sudanes | Q6: Riyadh | T6: active | U6: full time | V6: =N6/30/80*1.25 -> 5.4010417 | W6: 0 | X6: =N6*0.25 -> 2592.5 | Y6: 0 | Z6: =N6*0.1 -> 1037 | AA6: 0 | AB6: 0 | AC6: 0 | AD6: 0 | AE6: 0 | AF6: 0 | AG6: 0 | AH6: =N6*AG6 -> 0 | AI6: =(N6+X6)*0.02 -> 259.25 | AJ6: =N6/30*H6 -> 345.66667 | AK6: =N6/30*2.5 -> 864.16667 | AL6: 50 | AM6: 3
A7: MJ-004 | B7: AHMED ALSULTAN | C7: SALES MANAGER | D7: KAHID FOUAD | E7: GM | F7: 45839 | G7: =F7+365 -> 46204 | H7: =DATEDIF(F7, TODAY(), "Y") -> 0 | I7: 32928 | J7: =DATEDIF(I7, TODAY(), "Y") -> 36 | K7: F | L7: B | M7: =N7+X7+Z7+AA7+AB7+AC7+AD7+AE7+AG7 -> 13999.5 | N7: 10370 | O7: jor | P7: Jordan | Q7: Riyadh | S7: 2459354664 | T7: active | U7: full time | V7: =N7/30/80*1.25 -> 5.4010417 | W7: 0 | X7: =N7*0.25 -> 2592.5 | Z7: =N7*0.1 -> 1037 | AA7: 0 | AB7: 0 | AC7: 0 | AD7: 0 | AE7: 0 | AF7: 0 | AG7: 0 | AH7: =N7*AG7 -> 0 | AI7: =(N7+X7)*0.02 -> 259.25 | AJ7: =N7/30*H7 -> 0 | AK7: =N7/30*2.5 -> 864.16667
A8: MJ-005 | B8: HASSAN SALAH MOHAMMED | C8: HEAD OF.HR | D8: SABRI OMER | E8: Director Mangar | F8: 45597 | G8: =F8+365 -> 45962 | H8: =DATEDIF(F8, TODAY(), "Y") -> 1 | I8: 34700 | J8: =DATEDIF(I8, TODAY(), "Y") -> 31 | K8: F | L8: B | M8: =N8+X8+Z8+AA8+AB8+AC8+AD8+AE8+AG8 -> 3000 | N8: 2222.2222 | O8: SD | P8: Sudanes | Q8: Riyadh | T8: active | U8: full time | V8: =N8/30/80*1.25 -> 1.1574074 | W8: 0 | X8: =N8*0.25 -> 555.55556 | Z8: =N8*0.1 -> 222.22222 | AA8: 0 | AB8: 0 | AC8: 0 | AD8: 0 | AE8: 0 | AF8: 0 | AG8: 0 | AH8: =N8*AG8 -> 0 | AI8: =(N8+X8)*0.02 -> 55.555556 | AJ8: =N8/30*H8 -> 74.074074 | AK8: =N8/30*2.5 -> 185.18519
A9: MJ-006 | B9: OMER AWADALGED ALZAN | C9: HR ASSISTANT | D9: HASSANSASLAH | E9: HEAD OF.HR | F9: 45901 | G9: =F9+365 -> 46266 | H9: =DATEDIF(F9, TODAY(), "Y") -> 0 | I9: 35368 | J9: =DATEDIF(I9, TODAY(), "Y") -> 29 | K9: B | L9: B | M9: =N9+X9+Z9+AA9+AB9+AC9+AD9+AE9+AG9 -> 3500 | N9: 2592.5926 | O9: SD | P9: Sudanes | Q9: Riyadh | S9: 2536850510 | T9: active | U9: full time | V9: =N9/30/80*1.25 -> 1.3503086 | W9: 0 | X9: =N9*0.25 -> 648.14815 | Z9: =N9*0.1 -> 259.25926 | AA9: 0 | AB9: 0 | AC9: 0 | AD9: 0 | AE9: 0 | AF9: 0 | AG9: 0 | AH9: =N9*AG9 -> 0 | AI9: =(N9+X9)*0.02 -> 64.814815 | AJ9: =N9/30*H9 -> 0 | AK9: =N9/30*2.5 -> 216.04938
A10: MJ-007 | B10: MOHAMMAD SAIED | C10: ACCOUNTANT | D10: KAHID FOUAD | E10: GM | F10: 46054 | G10: =F10+365 -> 46419 | H10: =DATEDIF(F10, TODAY(), "Y") -> 0 | I10: 36708 | J10: =DATEDIF(I10, TODAY(), "Y") -> 25 | K10: F | L10: B | M10: =N10+X10+Z10+AA10+AB10+AC10+AD10+AE10+AG10 -> 3500 | N10: 2592.5926 | O10: EG | P10: Eygept | Q10: Riyadh | S10: 2564444343 | T10: active | U10: full time | V10: =N10/30/80*1.25 -> 1.3503086 | W10: 0 | X10: =N10*0.25 -> 648.14815 | Z10: =N10*0.1 -> 259.25926 | AA10: 0 | AB10: 0 | AC10: 0 | AD10: 0 | AE10: 0 | AF10: 0 | AG10: 0 | AH10: =N10*AG10 -> 0 | AI10: =(N10+X10)*0.02 -> 64.814815 | AJ10: =N10/30*H10 -> 0 | AK10: =N10/30*2.5 -> 216.04938
A11: MJ-008 | B11: HANI MOHAMMED | C11: IT LADER | D11: SABRI OMER | E11: Director Mangar | F11: 46054 | G11: =F11+365 -> 46419 | H11: =DATEDIF(F11, TODAY(), "Y") -> 0 | I11: 33043 | J11: =DATEDIF(I11, TODAY(), "Y") -> 35 | K11: F | L11: B | M11: =N11+X11+Z11+AA11+AB11+AC11+AD11+AE11+AG11 -> 4000 | N11: 2962.963 | O11: SD | P11: Sudanes | Q11: Riyadh | T11: active | U11: full time | V11: =N11/30/80*1.25 -> 1.5432099 | W11: 0 | X11: =N11*0.25 -> 740.74074 | Z11: =N11*0.1 -> 296.2963 | AA11: 0 | AB11: 0 | AC11: 0 | AD11: 0 | AE11: 0 | AF11: 0 | AG11: 0 | AH11: =N11*AG11 -> 0 | AI11: =(N11+X11)*0.02 -> 74.074074 | AJ11: =N11/30*H11 -> 0 | AK11: =N11/30*2.5 -> 246.91358
A12: MJ-009 | B12: LOAY MAHJUB ELSHAIKH | C12: SAELES | D12: AHMED SULTAN | E12: SALES MANAGER | F12: 46098 | G12: =F12+365 -> 46463 | H12: =DATEDIF(F12, TODAY(), "Y") -> 0 | I12: 32753 | J12: =DATEDIF(I12, TODAY(), "Y") -> 36 | K12: F | L12: B | M12: =N12+X12+Z12+AA12+AB12+AC12+AD12+AE12+AG12 -> 8500 | N12: 6296.2963 | O12: SD | P12: Sudanes | Q12: Riyadh | S12: 2499893903 | T12: active | U12: full time | V12: =N12/30/80*1.25 -> 3.279321 | W12: 0 | X12: =N12*0.25 -> 1574.0741 | Z12: =N12*0.1 -> 629.62963 | AA12: 0 | AB12: 0 | AC12: 0 | AD12: 0 | AE12: 0 | AF12: 0 | AG12: 0 | AH12: =N12*AG12 -> 0 | AI12: =(N12+X12)*0.02 -> 157.40741 | AJ12: =N12/30*H12 -> 0 | AK12: =N12/30*2.5 -> 524.69136
A13: MJ-010 | B13: Mohamad Yousef | C13: SAELES | D13: AHMED SULTAN | E13: SALES MANAGER | F13: 46113 | G13: =F13+365 -> 46478 | H13: =DATEDIF(F13, TODAY(), "Y") -> 0 | I13: 30655 | J13: =DATEDIF(I13, TODAY(), "Y") -> 42 | K13: F | L13: A+ | M13: =N13+X13+Z13+AA13+AB13+AC13+AD13+AE13+AG13 -> 25000 | N13: 18518.519 | O13: jor | P13: Jordan | Q13: Riyadh | S13: 2458701873 | T13: active | U13: full time | V13: =N13/30/80*1.25 -> 9.6450617 | W13: 1 | X13: =N13*0.25 -> 4629.6296 | Z13: =N13*0.1 -> 1851.8519 | AA13: 0 | AB13: 0 | AC13: 0 | AD13: 0 | AE13: 0 | AF13: 0 | AG13: 0 | AH13: =N13*AG13 -> 0 | AI13: =(N13+X13)*0.02 -> 462.96296 | AJ13: =N13/30*H13 -> 0 | AK13: =N13/30*2.5 -> 1543.2099
A14: MJ-011 | B14: MOHSIN JAMILKHALID JAMIL | C14: SALES EXECUTIVE | D14: AHMED SULTAN | E14: SALES MANAGER | F14: 45901 | G14: =F14+365 -> 46266 | H14: =DATEDIF(F14, TODAY(), "Y") -> 0 | I14: 31335 | J14: =DATEDIF(I14, TODAY(), "Y") -> 40 | K14: F | L14: B | M14: =N14+X14+Z14+AA14+AB14+AC14+AD14+AE14+AG14 -> 7500 | N14: 5555.5556 | O14: PK | P14: Pakistani | Q14: Madinah | S14: 2311419119 | T14: active | U14: full time | V14: =N14/30/80*1.25 -> 2.8935185 | W14: 0 | X14: =N14*0.25 -> 1388.8889 | Z14: =N14*0.1 -> 555.55556 | AA14: 0 | AB14: 0 | AC14: 0 | AD14: 0 | AE14: 0 | AF14: 0 | AG14: 0 | AH14: =N14*AG14 -> 0 | AI14: =(N14+X14)*0.02 -> 138.88889 | AJ14: =N14/30*H14 -> 0 | AK14: =N14/30*2.5 -> 462.96296
A15: MJ-012 | B15: MAZIN OSMAN MOHAMED | C15: HUBS SUPERVISOR | D15: SABRI OMER | E15: Director Mangar | F15: 46062 | G15: =F15+365 -> 46427 | H15: =DATEDIF(F15, TODAY(), "Y") -> 0 | I15: 30571 | J15: =DATEDIF(I15, TODAY(), "Y") -> 42 | K15: F | L15: B | M15: =N15+X15+Z15+AA15+AB15+AC15+AD15+AE15+AG15 -> 6000 | N15: 4444.4444 | O15: SD | P15: Sudanes | Q15: Riyadh | S15: 2571029764 | T15: active | U15: full time | V15: =N15/30/80*1.25 -> 2.3148148 | W15: 0 | X15: =N15*0.25 -> 1111.1111 | Z15: =N15*0.1 -> 444.44444 | AA15: 0 | AB15: 0 | AC15: 0 | AD15: 0 | AE15: 0 | AF15: 0 | AG15: 0 | AH15: =N15*AG15 -> 0 | AI15: =(N15+X15)*0.02 -> 111.11111 | AJ15: =N15/30*H15 -> 0 | AK15: =N15/30*2.5 -> 370.37037
A16: MJ-013 | B16: ALAAULDEEN ARABI | C16: FLEET SUPERVISOR | D16: MAZIN OSMAN | E16: HUBS SUPERVISOR | F16: 45848 | G16: =F16+365 -> 46213 | H16: =DATEDIF(F16, TODAY(), "Y") -> 0 | I16: 37633 | J16: =DATEDIF(I16, TODAY(), "Y") -> 23 | K16: B | L16: B | M16: =N16+X16+Z16+AA16+AB16+AC16+AD16+AE16+AG16 -> 4500 | N16: 3333.3333 | O16: SD | P16: Sudanes | Q16: jeddah | S16: 2196460311 | T16: active | U16: full time | V16: =N16/30/80*1.25 -> 1.7361111 | W16: 0 | X16: =N16*0.25 -> 833.33333 | Z16: =N16*0.1 -> 333.33333 | AA16: 0 | AB16: 0 | AC16: 0 | AD16: 0 | AE16: 0 | AF16: 0 | AG16: 0 | AH16: =N16*AG16 -> 0 | AI16: =(N16+X16)*0.02 -> 83.333333 | AJ16: =N16/30*H16 -> 0 | AK16: =N16/30*2.5 -> 277.77778
A17: MJ-014 | B17: MUHAND MOHAMMED | C17: FLEET SUPERVISOR | D17: ALAAULDEEN ARABI | E17: FLEET SUPERVISOR | F17: 46054 | G17: =F17+365 -> 46419 | H17: =DATEDIF(F17, TODAY(), "Y") -> 0 | I17: 33531 | J17: =DATEDIF(I17, TODAY(), "Y") -> 34 | K17: f | L17: B | M17: =N17+X17+Z17+AA17+AB17+AC17+AD17+AE17+AG17 -> 2500 | N17: 1851.8519 | O17: SD | P17: Sudanes | Q17: Riyadh | S17: 2482682800 | T17: active | U17: full time | V17: =N17/30/80*1.25 -> 0.96450617 | W17: 0 | X17: =N17*0.25 -> 462.96296 | Z17: =N17*0.1 -> 185.18519 | AA17: 0 | AB17: 0 | AC17: 0 | AD17: 0 | AE17: 0 | AF17: 0 | AG17: 0 | AH17: =N17*AG17 -> 0 | AI17: =(N17+X17)*0.02 -> 46.296296 | AJ17: =N17/30*H17 -> 0 | AK17: =N17/30*2.5 -> 154.32099
A18: MJ-015 | B18: MUZAMMAL MAQSOOD | C18: Taem Lader | D18: MAZIN OSMAN | E18: HUBS SUPERVISOR | F18: 45871 | G18: =F18+365 -> 46236 | H18: =DATEDIF(F18, TODAY(), "Y") -> 0 | I18: 34481 | J18: =DATEDIF(I18, TODAY(), "Y") -> 31 | K18: f | L18: B | M18: =N18+X18+Z18+AA18+AB18+AC18+AD18+AE18+AG18 -> 3500 | N18: 2592.5926 | O18: PK | P18: Pakistani | Q18: Riyadh | S18: 2578130706 | T18: active | U18: full time | V18: =N18/30/80*1.25 -> 1.3503086 | W18: 0 | X18: =N18*0.25 -> 648.14815 | Z18: =N18*0.1 -> 259.25926 | AA18: 0 | AB18: 0 | AC18: 0 | AD18: 0 | AE18: 0 | AF18: 0 | AG18: 0 | AH18: =N18*AG18 -> 0 | AI18: =(N18+X18)*0.02 -> 64.814815 | AJ18: =N18/30*H18 -> 0 | AK18: =N18/30*2.5 -> 216.04938
A19: MJ-016 | B19: REFAT MOHAMED AHMED | C19: HUB LADER | D19: MAZIN OSMAN | E19: HUBS SUPERVISOR | F19: 46064 | G19: =F19+365 -> 46429 | H19: =DATEDIF(F19, TODAY(), "Y") -> 0 | I19: 35995 | J19: =DATEDIF(I19, TODAY(), "Y") -> 27 | K19: F | L19: B | M19: =N19+X19+Z19+AA19+AB19+AC19+AD19+AE19+AG19 -> 3500 | N19: 2592.5926 | O19: SD | P19: Sudanes | Q19: Dammam | S19: 2525273385 | T19: active | U19: full time | V19: =N19/30/80*1.25 -> 1.3503086 | W19: 0 | X19: =N19*0.25 -> 648.14815 | Z19: =N19*0.1 -> 259.25926 | AA19: 0 | AB19: 0 | AC19: 0 | AD19: 0 | AE19: 0 | AF19: 0 | AG19: 0 | AH19: =N19*AG19 -> 0 | AI19: =(N19+X19)*0.02 -> 64.814815 | AJ19: =N19/30*H19 -> 0 | AK19: =N19/30*2.5 -> 216.04938
A20: MJ-017 | B20: KHALID ABDU QAYID GHALIB | C20: HUB LADER | D20: MAZIN OSMAN | E20: HUBS SUPERVISOR | F20: 46062 | G20: =F20+365 -> 46427 | H20: =DATEDIF(F20, TODAY(), "Y") -> 0 | I20: 31499 | J20: =DATEDIF(I20, TODAY(), "Y") -> 40 | K20: F | L20: B | M20: =N20+X20+Z20+AA20+AB20+AC20+AD20+AE20+AG20 -> 5000 | N20: 3703.7037 | O20: YE | P20: Yemeni | Q20: jeddah | S20: 20580559268 | T20: active | U20: full time | V20: =N20/30/80*1.25 -> 1.9290123 | W20: 0 | X20: =N20*0.25 -> 925.92593 | Z20: =N20*0.1 -> 370.37037 | AA20: 0 | AB20: 0 | AC20: 0 | AD20: 0 | AE20: 0 | AF20: 0 | AG20: 0 | AH20: =N20*AG20 -> 0 | AI20: =(N20+X20)*0.02 -> 92.592593 | AJ20: =N20/30*H20 -> 0 | AK20: =N20/30*2.5 -> 308.64198
A21: MJ-018 | B21: ISMAIL MOHAMED IBRAHIM | C21: HUB LADER | D21: MAZIN OSMAN | E21: HUBS SUPERVISOR | F21: 46084 | G21: =F21+365 -> 46449 | H21: =DATEDIF(F21, TODAY(), "Y") -> 0 | I21: 35081 | J21: =DATEDIF(I21, TODAY(), "Y") -> 30 | K21: B | L21: B | M21: =N21+X21+Z21+AA21+AB21+AC21+AD21+AE21+AG21 -> 3500.55 | N21: 2593 | O21: SD | P21: Sudanes | Q21: Madinah | S21: 2570618336 | T21: active | U21: full time | V21: =N21/30/80*1.25 -> 1.3505208 | X21: =N21*0.25 -> 648.25 | Z21: =N21*0.1 -> 259.3 | AF21: 0 | AG21: 0 | AI21: =(N21+X21)*0.02 -> 64.825 | AJ21: =N21/30*H21 -> 0 | AK21: =N21/30*2.5 -> 216.08333
A22: MJ-019 | B22: BADR AHMED AHMED ALISHARAF | C22: Casher | D22: MOHAMMAD SAIED | E22: ACCOUNTANT | F22: 46065 | G22: =F22+365 -> 46430 | H22: =DATEDIF(F22, TODAY(), "Y") -> 0 | I22: 34553 | J22: =DATEDIF(I22, TODAY(), "Y") -> 31 | K22: B | L22: B | M22: =N22+X22+Z22+AA22+AB22+AC22+AD22+AE22+AG22 -> 3500 | N22: 2592.5926 | O22: YE | P22: Yemeni | Q22: jeddah | S22: 2466410095 | T22: active | U22: full time | V22: =N22/30/80*1.25 -> 1.3503086 | W22: 0 | X22: =N22*0.25 -> 648.14815 | Z22: =N22*0.1 -> 259.25926 | AA22: 0 | AB22: 0 | AC22: 0 | AD22: 0 | AE22: 0 | AF22: 0 | AG22: 0 | AH22: =N22*AG22 -> 0 | AI22: =(N22+X22)*0.02 -> 64.814815 | AJ22: =N22/30*H22 -> 0 | AK22: =N22/30*2.5 -> 216.04938
A23: MJ-020 | B23: KAMRUL MD JOYDAL | C23: LAYPPER | D23: MUZAMMAL MAQSOOD | E23: Taem Lader | F23: 45778 | G23: =F23+365 -> 46143 | H23: =DATEDIF(F23, TODAY(), "Y") -> 0 | I23: 33878 | J23: =DATEDIF(I23, TODAY(), "Y") -> 33 | K23: F | L23: B | M23: =N23+X23+Z23+AA23+AB23+AC23+AD23+AE23+AG23 -> 2500 | N23: 1851.8519 | O23: BD | P23: Bangldeshi | Q23: Riyadh | S23: 2505872222 | T23: active | U23: full time | V23: =N23/30/80*1.25 -> 0.96450617 | W23: 0 | X23: =N23*0.25 -> 462.96296 | Z23: =N23*0.1 -> 185.18519 | AA23: 0 | AB23: 0 | AC23: 0 | AD23: 0 | AE23: 0 | AF23: 0 | AG23: 0 | AH23: =N23*AG23 -> 0 | AI23: =(N23+X23)*0.02 -> 46.296296 | AJ23: =N23/30*H23 -> 0 | AK23: =N23/30*2.5 -> 154.32099
A24: MJ-021 | B24: RAIHADAHAMMAD | C24: LAYPPER | D24: MUZAMMAL MAQSOOD | E24: Taem Lader | F24: 46114 | G24: =F24+365 -> 46479 | H24: =DATEDIF(F24, TODAY(), "Y") -> 0 | I24: 37762 | J24: =DATEDIF(I24, TODAY(), "Y") -> 22 | K24: B | L24: B | M24: =N24+X24+Z24+AA24+AB24+AC24+AD24+AE24+AG24 -> 2000 | N24: 1481.4815 | O24: BD | P24: Bangldeshi | Q24: Riyadh | S24: 2620512919 | T24: active | U24: full time | V24: =N24/30/80*1.25 -> 0.77160494 | W24: 0 | X24: =N24*0.25 -> 370.37037 | Z24: =N24*0.1 -> 148.14815 | AA24: 0 | AB24: 0 | AC24: 0 | AD24: 0 | AE24: 0 | AF24: 0 | AG24: 0 | AH24: =N24*AG24 -> 0 | AI24: =(N24+X24)*0.02 -> 37.037037 | AJ24: =N24/30*H24 -> 0 | AK24: =N24/30*2.5 -> 123.45679
A25: MJ-022 | B25: ARIF SARKER | C25: OFFICEBOY | D25: OMER AWADALGED | E25: HR ASSISTANT | F25: 46105 | G25: =F25+365 -> 46470 | H25: =DATEDIF(F25, TODAY(), "Y") -> 0 | I25: 32873 | J25: =DATEDIF(I25, TODAY(), "Y") -> 36 | K25: F | L25: B | M25: =N25+X25+Z25+AA25+AB25+AC25+AD25+AE25+AG25 -> 2000 | N25: 1481.4815 | O25: BD | P25: Bangldeshi | Q25: Riyadh | S25: 2444225607 | T25: active | U25: full time | V25: =N25/30/80*1.25 -> 0.77160494 | W25: 0 | X25: =N25*0.25 -> 370.37037 | Z25: =N25*0.1 -> 148.14815 | AA25: 0 | AB25: 0 | AC25: 0 | AD25: 0 | AE25: 0 | AF25: 0 | AG25: 0 | AH25: =N25*AG25 -> 0 | AI25: =(N25+X25)*0.02 -> 37.037037 | AJ25: =N25/30*H25 -> 0 | AK25: =N25/30*2.5 -> 123.45679
A26: MJ-023 | B26: MOHAMMED YAHYA THAPT | C26: courier | D26: MUZAMMAL MAQSOOD | E26: Taem Lader | F26: 46092 | G26: =F26+365 -> 46457 | H26: =DATEDIF(F26, TODAY(), "Y") -> 0 | I26: 32363 | J26: =DATEDIF(I26, TODAY(), "Y") -> 37 | K26: F | L26: B | M26: =N26+X26+Z26+AA26+AB26+AC26+AD26+AE26+AG26 -> 3500 | N26: 2592.5926 | O26: YE | P26: Yemeni | Q26: Riyadh | S26: 2572409825 | T26: active | U26: full time | V26: =N26/30/80*1.25 -> 1.3503086 | W26: 0 | X26: =N26*0.25 -> 648.14815 | Z26: =N26*0.1 -> 259.25926 | AA26: 0 | AB26: 0 | AC26: 0 | AD26: 0 | AE26: 0 | AF26: 0 | AG26: 0 | AH26: =N26*AG26 -> 0 | AI26: =(N26+X26)*0.02 -> 64.814815 | AJ26: =N26/30*H26 -> 0 | AK26: =N26/30*2.5 -> 216.04938
A27: MJ-024 | B27: MUHAMMAD SHAHBAZ HUSSAIN | C27: courier | D27: MUZAMMAL MAQSOOD | E27: Taem Lader | F27: 45859 | G27: =F27+365 -> 46224 | H27: =DATEDIF(F27, TODAY(), "Y") -> 0 | I27: 30066 | J27: =DATEDIF(I27, TODAY(), "Y") -> 43 | K27: F | L27: B | M27: =N27+X27+Z27+AA27+AB27+AC27+AD27+AE27+AG27 -> 3000 | N27: 2222.2222 | O27: PK | P27: Pakistani | Q27: Riyadh | S27: 2603959731 | T27: active | U27: full time | V27: =N27/30/80*1.25 -> 1.1574074 | W27: 0 | X27: =N27*0.25 -> 555.55556 | Z27: =N27*0.1 -> 222.22222 | AA27: 0 | AB27: 0 | AC27: 0 | AD27: 0 | AE27: 0 | AF27: 0 | AG27: 0 | AH27: =N27*AG27 -> 0 | AI27: =(N27+X27)*0.02 -> 55.555556 | AJ27: =N27/30*H27 -> 0 | AK27: =N27/30*2.5 -> 185.18519
A28: MJ-025 | B28: SHAHZAIB ALI SHABBIR AHMED | C28: courier | D28: MUZAMMAL MAQSOOD | E28: Taem Lader | F28: 45859 | G28: =F28+365 -> 46224 | H28: =DATEDIF(F28, TODAY(), "Y") -> 0 | I28: 36947 | J28: =DATEDIF(I28, TODAY(), "Y") -> 25 | K28: B | L28: B | M28: =N28+X28+Z28+AA28+AB28+AC28+AD28+AE28+AG28 -> 3000 | N28: 2222.2222 | O28: PK | P28: Pakistani | Q28: Riyadh | S28: 2527077107 | T28: active | U28: full time | V28: =N28/30/80*1.25 -> 1.1574074 | W28: 0 | X28: =N28*0.25 -> 555.55556 | Z28: =N28*0.1 -> 222.22222 | AA28: 0 | AB28: 0 | AC28: 0 | AD28: 0 | AE28: 0 | AF28: 0 | AG28: 0 | AH28: =N28*AG28 -> 0 | AI28: =(N28+X28)*0.02 -> 55.555556 | AJ28: =N28/30*H28 -> 0 | AK28: =N28/30*2.5 -> 185.18519
A29: MJ-026 | B29: SAQLAIN ABBAS LIAQAT HUSSAIN | C29: courier | D29: MUZAMMAL MAQSOOD | E29: Taem Lader | F29: 45859 | G29: =F29+365 -> 46224 | H29: =DATEDIF(F29, TODAY(), "Y") -> 0 | I29: 36698 | J29: =DATEDIF(I29, TODAY(), "Y") -> 25 | K29: B | L29: B | M29: =N29+X29+Z29+AA29+AB29+AC29+AD29+AE29+AG29 -> 3000 | N29: 2222.2222 | O29: PK | P29: Pakistani | Q29: Riyadh | S29: 2566762213 | T29: active | U29: full time | V29: =N29/30/80*1.25 -> 1.1574074 | W29: 0 | X29: =N29*0.25 -> 555.55556 | Z29: =N29*0.1 -> 222.22222 | AA29: 0 | AB29: 0 | AC29: 0 | AD29: 0 | AE29: 0 | AF29: 0 | AG29: 0 | AH29: =N29*AG29 -> 0 | AI29: =(N29+X29)*0.02 -> 55.555556 | AJ29: =N29/30*H29 -> 0 | AK29: =N29/30*2.5 -> 185.18519
A30: MJ-027 | B30: AKTER MATUBBER | C30: courier | D30: MUZAMMAL MAQSOOD | E30: Taem Lader | F30: 46113 | G30: =F30+365 -> 46478 | H30: =DATEDIF(F30, TODAY(), "Y") -> 0 | I30: 31977 | J30: =DATEDIF(I30, TODAY(), "Y") -> 38 | K30: f | L30: B | M30: =N30+X30+Z30+AA30+AB30+AC30+AD30+AE30+AG30 -> 2500.2 | N30: 1852 | O30: BD | P30: Bangldeshi | Q30: Riyadh | S30: 2508287634 | T30: active | U30: full time | V30: =N30/30/80*1.25 -> 0.96458333 | X30: =N30*0.25 -> 463 | Z30: =N30*0.1 -> 185.2 | AA30: 0 | AB30: 0 | AC30: 0 | AD30: 0 | AE30: 0 | AF30: 0 | AG30: 0 | AH30: =N30*AG30 -> 0 | AI30: =(N30+X30)*0.02 -> 46.3 | AJ30: =N30/30*H30 -> 0 | AK30: =N30/30*2.5 -> 154.33333
A31: MJ-028 | B31: NASSAR THABIT ALIAL | C31: courier | D31: MUZAMMAL MAQSOOD | E31: Taem Lader | F31: 46078 | G31: =F31+365 -> 46443 | H31: =DATEDIF(F31, TODAY(), "Y") -> 0 | I31: 36244 | J31: =DATEDIF(I31, TODAY(), "Y") -> 27 | K31: B | L31: B | M31: =N31+X31+Z31+AA31+AB31+AC31+AD31+AE31+AG31 -> 3500 | N31: 2592.5926 | O31: YE | P31: Pakistani | Q31: Qasim | S31: 2501909184 | T31: active | U31: full time | V31: =N31/30/80*1.25 -> 1.3503086 | W31: 0 | X31: =N31*0.25 -> 648.14815 | Z31: =N31*0.1 -> 259.25926 | AA31: 0 | AB31: 0 | AC31: 0 | AD31: 0 | AE31: 0 | AF31: 0 | AG31: 0 | AH31: =N31*AG31 -> 0 | AI31: =(N31+X31)*0.02 -> 64.814815 | AJ31: =N31/30*H31 -> 0 | AK31: =N31/30*2.5 -> 216.04938
A32: MJ-029 | B32: RAFAT MOHAMED AHMEDADAM | C32: courier | D32: REFAT MOHAMED AHMED | E32: HUB LADER | F32: 46078 | G32: =F32+365 -> 46443 | H32: =DATEDIF(F32, TODAY(), "Y") -> 0 | I32: 35446 | J32: =DATEDIF(I32, TODAY(), "Y") -> 29 | K32: B | L32: B | M32: =N32+X32+Z32+AA32+AB32+AC32+AD32+AE32+AG32 -> 3500 | N32: 2592.5926 | O32: SD | P32: Sudanes | Q32: Dammam | S32: 2503552719 | T32: active | U32: full time | V32: =N32/30/80*1.25 -> 1.3503086 | W32: 0 | X32: =N32*0.25 -> 648.14815 | Z32: =N32*0.1 -> 259.25926 | AA32: 0 | AB32: 0 | AC32: 0 | AD32: 0 | AE32: 0 | AF32: 0 | AG32: 0 | AH32: =N32*AG32 -> 0 | AI32: =(N32+X32)*0.02 -> 64.814815 | AJ32: =N32/30*H32 -> 0 | AK32: =N32/30*2.5 -> 216.04938
A33: MJ-030 | B33: NUMAN SHUBAYR KALAMIAH | C33: courier | D33: ISMAIL MOHAMED | E33: Taem Lader | F33: 45903 | G33: =F33+365 -> 46268 | H33: =DATEDIF(F33, TODAY(), "Y") -> 0 | I33: 36267 | J33: =DATEDIF(I33, TODAY(), "Y") -> 27 | K33: B | L33: B | M33: =N33+X33+Z33+AA33+AB33+AC33+AD33+AE33+AG33 -> 3000 | N33: 2222.2222 | O33: MMR | P33: Mynamar | Q33: jeddah | S33: 2213094820 | T33: active | U33: full time | V33: =N33/30/80*1.25 -> 1.1574074 | W33: 0 | X33: =N33*0.25 -> 555.55556 | Z33: =N33*0.1 -> 222.22222 | AA33: 0 | AB33: 0 | AC33: 0 | AD33: 0 | AE33: 0 | AF33: 0 | AG33: 0 | AH33: =N33*AG33 -> 0 | AI33: =(N33+X33)*0.02 -> 55.555556 | AJ33: =N33/30*H33 -> 0 | AK33: =N33/30*2.5 -> 185.18519
A34: MJ-031 | B34: AMEEN ABDO MOHAMMED | C34: courier | D34: ISMAIL MOHAMED | E34: Taem Lader | F34: 45902 | G34: =F34+365 -> 46267 | H34: =DATEDIF(F34, TODAY(), "Y") -> 0 | I34: 29952 | J34: =DATEDIF(I34, TODAY(), "Y") -> 44 | K34: F | L34: B | M34: =N34+X34+Z34+AA34+AB34+AC34+AD34+AE34+AG34 -> 3000 | N34: 2222.2222 | O34: YE | P34: Yemeni | Q34: jeddah | S34: 2252283344 | T34: active | U34: full time | V34: =N34/30/80*1.25 -> 1.1574074 | W34: 0 | X34: =N34*0.25 -> 555.55556 | Z34: =N34*0.1 -> 222.22222 | AA34: 0 | AB34: 0 | AC34: 0 | AD34: 0 | AE34: 0 | AF34: 0 | AG34: 0 | AH34: =N34*AG34 -> 0 | AI34: =(N34+X34)*0.02 -> 55.555556 | AJ34: =N34/30*H34 -> 0 | AK34: =N34/30*2.5 -> 185.18519
A35: MJ-032 | B35: MOHAMMED NOOR ALAM | C35: courier | D35: ISMAIL MOHAMED | E35: Taem Lader | F35: 46113 | G35: =F35+365 -> 46478 | H35: =DATEDIF(F35, TODAY(), "Y") -> 0 | I35: 38245 | J35: =DATEDIF(I35, TODAY(), "Y") -> 21 | K35: B | L35: B | M35: =N35+X35+Z35+AA35+AB35+AC35+AD35+AE35+AG35 -> 2500.2 | N35: 1852 | O35: MMR | P35: Mynamar | Q35: jeddah | S35: 2400449498 | T35: active | U35: full time | V35: =N35/30/80*1.25 -> 0.96458333 | W35: 0 | X35: =N35*0.25 -> 463 | Z35: =N35*0.1 -> 185.2 | AA35: 0 | AB35: 0 | AC35: 0 | AD35: 0 | AE35: 0 | AF35: 0 | AG35: 0 | AH35: =N35*AG35 -> 0 | AI35: =(N35+X35)*0.02 -> 46.3 | AJ35: =N35/30*H35 -> 0 | AK35: =N35/30*2.5 -> 154.33333
A36: MJ-033 | B36: MOHAMMED ALI ABAKAR | C36: courier | D36: ISMAIL MOHAMED | E36: Taem Lader | F36: 46113 | G36: =F36+365 -> 46478 | H36: =DATEDIF(F36, TODAY(), "Y") -> 0 | I36: 35220 | J36: =DATEDIF(I36, TODAY(), "Y") -> 29 | K36: B | L36: B | M36: =N36+X36+Z36+AA36+AB36+AC36+AD36+AE36+AG36 -> 2500.2 | N36: 1852 | O36: CH | P36: CHAD | Q36: jeddah | S36: 2169463185 | T36: active | U36: full time | V36: =N36/30/80*1.25 -> 0.96458333 | W36: 0 | X36: =N36*0.25 -> 463 | Z36: =N36*0.1 -> 185.2 | AA36: 0 | AB36: 0 | AC36: 0 | AD36: 0 | AE36: 0 | AF36: 0 | AG36: 0 | AH36: =N36*AG36 -> 0 | AI36: =(N36+X36)*0.02 -> 46.3 | AJ36: =N36/30*H36 -> 0 | AK36: =N36/30*2.5 -> 154.33333
A37: MJ-034 | B37: Mohammed abdalla hamad | C37: courier | D37: REFAT MOHAMED | E37: Taem Lader | F37: 46110 | G37: =F37+365 -> 46475 | H37: =DATEDIF(F37, TODAY(), "Y") -> 0 | I37: 35591 | J37: =DATEDIF(I37, TODAY(), "Y") -> 28 | K37: B | L37: B | M37: =N37+X37+Z37+AA37+AB37+AC37+AD37+AE37+AG37 -> 2500.2 | N37: 1852 | O37: SD | P37: Sudanes | Q37: Dammam | S37: 2544955715 | T37: active | U37: full time | V37: =N37/30/80*1.25 -> 0.96458333 | X37: =N37*0.25 -> 463 | Z37: =N37*0.1 -> 185.2 | AA37: 0 | AB37: 0 | AC37: 0 | AD37: 0 | AE37: 0 | AF37: 0 | AG37: 0 | AH37: =N37*AG37 -> 0 | AI37: =(N37+X37)*0.02 -> 46.3 | AJ37: =N37/30*H37 -> 0 | AK37: =N37/30*2.5 -> 154.33333
A39: TOTAL | M39: =SUM(M4:M37) -> 186999.85

Sheet Annual Leave Taruking
D3: Annual Leave tarucking
A7: Emp-ID | B7: Employee Name | C7: Basic Salary | D7: Annual Leave Entitlement (Days) | E7: Leave Taken (Days) | F7: Daily Wage | G7: Accrued Leave (Days) | H7: Remaining Leave (Days) | I7: Leave Value
A8: =employee_master1!A4 -> MJ-001 | B8: =employee_master1!B4 -> KHALID FOUAD | C8: =employee_master1!N4 -> 11851.852 | D8: =IF(TODAY()-employee_master1!F4>=365,21,0) -> 0 | F8: =C8/30 -> 395.06173 | G8: =D8 -> 0 | H8: =G8-E8 -> 0 | I8: =F8*H8 -> 0
A9: =employee_master1!A5 -> MJ-002 | B9: =employee_master1!B5 -> SABRI OMER | C9: =employee_master1!N5 -> 10370 | D9: =IF(TODAY()-employee_master1!F5>=365,21,0) -> 21 | F9: =C9/30 -> 345.66667 | G9: =D9 -> 21 | H9: =G9-E9 -> 21 | I9: =F9*H9 -> 7259
A10: =employee_master1!A6 -> MJ-003 | B10: =employee_master1!B6 -> MOHAMMED ALARABI | C10: =employee_master1!N6 -> 10370 | D10: =IF(TODAY()-employee_master1!F6>=365,21,0) -> 21 | F10: =C10/30 -> 345.66667 | G10: =D10 -> 21 | H10: =G10-E10 -> 21 | I10: =F10*H10 -> 7259
A11: =employee_master1!A7 -> MJ-004 | B11: =employee_master1!B7 -> AHMED ALSULTAN | C11: =employee_master1!N7 -> 10370 | D11: =IF(TODAY()-employee_master1!F7>=365,21,0) -> 0 | F11: =C11/30 -> 345.66667 | G11: =D11 -> 0 | H11: =G11-E11 -> 0 | I11: =F11*H11 -> 0
A12: =employee_master1!A8 -> MJ-005 | B12: =employee_master1!B8 -> HASSAN SALAH MOHAMMED | C12: =employee_master1!N8 -> 2222.2222 | D12: =IF(TODAY()-employee_master1!F8>=365,21,0) -> 21 | F12: =C12/30 -> 74.074074 | G12: =D12 -> 21 | H12: =G12-E12 -> 21 | I12: =F12*H12 -> 1555.5556
A13: =employee_master1!A9 -> MJ-006 | B13: =employee_master1!B9 -> OMER AWADALGED ALZAN | C13: =employee_master1!N9 -> 2592.5926 | D13: =IF(TODAY()-employee_master1!F9>=365,21,0) -> 0 | F13: =C13/30 -> 86.419753 | G13: =D13 -> 0 | H13: =G13-E13 -> 0 | I13: =F13*H13 -> 0
A14: =employee_master1!A10 -> MJ-007 | B14: =employee_master1!B10 -> MOHAMMAD SAIED | C14: =employee_master1!N10 -> 2592.5926 | D14: =IF(TODAY()-employee_master1!F10>=365,21,0) -> 0 | F14: =C14/30 -> 86.419753 | G14: =D14 -> 0 | H14: =G14-E14 -> 0 | I14: =F14*H14 -> 0
A15: =employee_master1!A11 -> MJ-008 | B15: =employee_master1!B11 -> HANI MOHAMMED | C15: =employee_master1!N11 -> 2962.963 | D15: =IF(TODAY()-employee_master1!F11>=365,21,0) -> 0 | F15: =C15/30 -> 98.765432 | G15: =D15 -> 0 | H15: =G15-E15 -> 0 | I15: =F15*H15 -> 0
A16: =employee_master1!A12 -> MJ-009 | B16: =employee_master1!B12 -> LOAY MAHJUB ELSHAIKH | C16: =employee_master1!N12 -> 6296.2963 | D16: =IF(TODAY()-employee_master1!F12>=365,21,0) -> 0 | F16: =C16/30 -> 209.87654 | G16: =D16 -> 0 | H16: =G16-E16 -> 0 | I16: =F16*H16 -> 0
A17: =employee_master1!A13 -> MJ-010 | B17: =employee_master1!B13 -> Mohamad Yousef | C17: =employee_master1!N13 -> 18518.519 | D17: =IF(TODAY()-employee_master1!F13>=365,21,0) -> 0 | F17: =C17/30 -> 617.28395 | G17: =D17 -> 0 | H17: =G17-E17 -> 0 | I17: =F17*H17 -> 0
A18: =employee_master1!A14 -> MJ-011 | B18: =employee_master1!B14 -> MOHSIN JAMILKHALID JAMIL | C18: =employee_master1!N14 -> 5555.5556 | D18: =IF(TODAY()-employee_master1!F14>=365,21,0) -> 0 | F18: =C18/30 -> 185.18519 | G18: =D18 -> 0 | H18: =G18-E18 -> 0 | I18: =F18*H18 -> 0
A19: =employee_master1!A15 -> MJ-012 | B19: =employee_master1!B15 -> MAZIN OSMAN MOHAMED | C19: =employee_master1!N15 -> 4444.4444 | D19: =IF(TODAY()-employee_master1!F15>=365,21,0) -> 0 | F19: =C19/30 -> 148.14815 | G19: =D19 -> 0 | H19: =G19-E19 -> 0 | I19: =F19*H19 -> 0
... A41: =employee_master1!A37 -> MJ-034 | B41: =employee_master1!B37 -> Mohammed abdalla hamad | C41: =employee_master1!N37 -> 1852 | D41: =IF(TODAY()-employee_master1!F37>=365,21,0) -> 0 | F41: =C41/30 -> 61.733333 | G41: =D41 -> 0 | H41: =G41-E41 -> 0 | I41: =F41*H41 -> 0
A44: =employee_master1!A39 -> TOTAL | C44: =employee_master1!N39 -> 0 | D44: =IF(TODAY()-employee_master1!F39>=365,21,0) -> 21 | F44: =C44/30 -> 0 | G44: =D44 -> 21 | H44: =G44-E44 -> 21 | I44: =F44*H44 -> 0
